LICENSE
README.md
setup.py
izzet/__init__.py
izzet/exceptions.py
izzet/memo.py
izzet/type_checkers.py
izzet/utils.py
izzet.egg-info/PKG-INFO
izzet.egg-info/SOURCES.txt
izzet.egg-info/dependency_links.txt
izzet.egg-info/top_level.txt
tests/__init__.py
tests/test_izzet.py