Metadata-Version: 2.1
Name: izzet
Version: 1.0.0
Summary: Easy and reliable way to verify that a given input matches a given class or generic type instance - and nothing else. 
Home-page: https://github.com/slightly-better-python/izzet
Author: Peter Wensel
Author-email: pwensel@gmail.com
License: UNKNOWN
Platform: UNKNOWN
Classifier: Programming Language :: Python :: 3
Classifier: License :: OSI Approved :: MIT License
Classifier: Operating System :: OS Independent
Requires-Python: >=3.6
License-File: LICENSE
